poktbot/__init__.py
poktbot/constants.py
poktbot/main.py
poktbot/api/__init__.py
poktbot/api/api.py
poktbot/api/observer.py
poktbot/api/node/__init__.py
poktbot/api/node/node.py
poktbot/api/node/node_transactions.py
poktbot/api/price/__init__.py
poktbot/api/price/coingecko.py
poktbot/api/releases/__init__.py
poktbot/api/releases/pypi.py
poktbot/callbacks/__init__.py
poktbot/callbacks/callback_notify_release.py
poktbot/callbacks/callback_store_prices.py
poktbot/callbacks/callback_store_transactions.py
poktbot/config/__init__.py
poktbot/config/config.py
poktbot/config/config_scheme.yaml
poktbot/config/ini/__init__.py
poktbot/config/ini/config.py
poktbot/config/json/__init__.py
poktbot/config/json/config.py
poktbot/config/os/__init__.py
poktbot/config/os/config.py
poktbot/config/yaml/__init__.py
poktbot/config/yaml/config.py
poktbot/log/__init__.py
poktbot/log/poktbot_logging.py
poktbot/storage/__init__.py
poktbot/storage/relay_db.py
poktbot/storage/local/__init__.py
poktbot/storage/local/joblib/__init__.py
poktbot/storage/local/joblib/relay_db_jl.py
poktbot/telegram/__init__.py
poktbot/telegram/bot.py
poktbot/telegram/exceptions/__init__.py
poktbot/telegram/exceptions/rbac_error.py
poktbot/telegram/layouts/admin.yaml
poktbot/telegram/layouts/investor.yaml
poktbot/telegram/layouts/sysadmin.yaml
poktbot/telegram/rbac/__init__.py
poktbot/telegram/rbac/role.py
poktbot/telegram/rbac/atomic/__init__.py
poktbot/telegram/rbac/atomic/balances.py
poktbot/telegram/rbac/atomic/info.py
poktbot/telegram/rbac/atomic/nodes.py
poktbot/telegram/rbac/atomic/server.py
poktbot/telegram/rbac/atomic/stats.py
poktbot/telegram/rbac/atomic/users.py
poktbot/telegram/rbac/composite/__init__.py
poktbot/telegram/rbac/composite/admin.py
poktbot/telegram/rbac/composite/investor.py
poktbot/telegram/rbac/composite/sysadmin.py
poktbot/utils/__init__.py
poktbot/utils/decorators.py
poktbot/utils/dotdict.py
poktbot/utils/formatting.py
poktbot/utils/periodic.py
poktbot/utils/telegram.py
poktbot-0.1.3.dist-info/LICENSE
poktbot-0.1.3.dist-info/METADATA
poktbot-0.1.3.dist-info/WHEEL
poktbot-0.1.3.dist-info/entry_points.txt
poktbot-0.1.3.dist-info/top_level.txt
poktbot-0.1.3.dist-info/RECORD
