Metadata-Version: 2.1
Name: poktbot
Version: 0.1.3
Summary: Pocket telegram bot for handling nodes tracking information and stats
Home-page: https://github.com/cryptonglab/poktbot
License: UNKNOWN
Keywords: pocket,bot,telegram,cryptocurrency,nodes,information,tracking,managing,system
Platform: UNKNOWN
Requires-Dist: Telethon (==1.10.8)
Requires-Dist: pandas (==1.3.5)
Requires-Dist: numpy (==1.21.5)
Requires-Dist: pyyaml (==6.0)
Requires-Dist: joblib (==1.1.0)
Requires-Dist: lz4 (==4.0.0)
Requires-Dist: bokeh (==2.4.2)
Requires-Dist: XlsxWriter (==3.0.3)
Requires-Dist: openpyxl (==3.0.9)
Requires-Dist: plotly (==5.6.0)
Requires-Dist: requests (==2.27.1)
Requires-Dist: matplotlib (==3.5.1)
Requires-Dist: selenium (==4.1.0)
